beatboard/__init__.py
beatboard/__main__.py
beatboard/args.py
beatboard/color_gen.py
beatboard/globs.py
beatboard/hardware.py
beatboard/logs.py
beatboard/playerctl.py
beatboard/utils.py
beatboard/G213Colors/G213Colors.py
beatboard/G213Colors/LICENSE
beatboard/G213Colors/README.md
beatboard/cache/__init__.py
beatboard/cache/colors.py
beatboard/cache/db.py
beatboard/cache/migrations/00_create_migration_table.sql
beatboard/cache/migrations/01_create_colors_cache_table.sql
beatboard-0.1.2.dist-info/licenses/LICENSE
pcaps/breathing.pcap
pcaps/breathing2.pcap
pcaps/cycle.pcap
pcaps/cycle2.pcap
pcaps/cycle_fast.pcap
pcaps/cycle_slow.pcap
pcaps/fields.pcap
pcaps/fields1.pcap
pcaps/game_key.pcap
pcaps/wave.pcap
pcaps/wave2.pcap
beatboard-0.1.2.dist-info/METADATA
beatboard-0.1.2.dist-info/WHEEL
beatboard-0.1.2.dist-info/entry_points.txt
beatboard-0.1.2.dist-info/top_level.txt
beatboard-0.1.2.dist-info/RECORD
