Metadata-Version: 2.4
Name: BeatBoard
Version: 0.1.2
Summary: Dynamic keyboard RGB lighting based on Spotify album art
License-Expression: MIT
Project-URL: Homepage, https://github.com/abdellatif-temsamani/BeatBoard
Project-URL: Repository, https://github.com/abdellatif-temsamani/BeatBoard
Project-URL: Issues, https://github.com/abdellatif-temsamani/BeatBoard/issues
Project-URL: Changelog, https://github.com/abdellatif-temsamani/BeatBoard/blob/main/CHANGELOG.md
Classifier: Development Status :: 4 - Beta
Classifier: Intended Audience :: End Users/Desktop
Classifier: Environment :: Console
Classifier: Operating System :: POSIX :: Linux
Classifier: Programming Language :: Python :: 3
Classifier: Programming Language :: Python :: 3.11
Classifier: Programming Language :: Python :: 3.12
Classifier: Topic :: Multimedia :: Sound/Audio :: Players
Requires-Python: >=3.11
License-File: LICENSE
Requires-Dist: certifi==2025.10.5
Requires-Dist: charset-normalizer==3.4.4
Requires-Dist: colorthief==0.2.1
Requires-Dist: contourpy==1.3.3
Requires-Dist: cycler==0.12.1
Requires-Dist: fonttools==4.61.0
Requires-Dist: idna==3.11
Requires-Dist: kiwisolver==1.4.9
Requires-Dist: markdown-it-py==3.0.0
Requires-Dist: matplotlib==3.10.7
Requires-Dist: mdurl==0.1.2
Requires-Dist: numpy==2.3.4
Requires-Dist: packaging==25.0
Requires-Dist: pillow==12.0.0
Requires-Dist: Pygments==2.19.2
Requires-Dist: pyparsing==3.2.5
Requires-Dist: python-dateutil==2.9.0.post0
Requires-Dist: pyusb==1.3.1
Requires-Dist: randomcolor==0.4.4.6
Requires-Dist: requests==2.32.5
Requires-Dist: rich==14.2.0
Requires-Dist: setuptools-scm==8.1.0
Requires-Dist: six==1.17.0
Requires-Dist: urllib3==2.6.1
Provides-Extra: dev
Requires-Dist: pytest==8.3.3; extra == "dev"
Requires-Dist: pytest-asyncio==1.3.0; extra == "dev"
Requires-Dist: ruff==0.14.8; extra == "dev"
Requires-Dist: build==1.3.0; extra == "dev"
Requires-Dist: pip-audit==2.7.3; extra == "dev"
Dynamic: license-file
